infinity_institute/__init__.py
infinity_institute/client.py
infinity_institute/models.py
infinity_institute/py.typed
infinity_institute/setup.py
infinity_institute-0.1.0.dist-info/licenses/LICENSE
infinity_institute-0.1.0.dist-info/METADATA
infinity_institute-0.1.0.dist-info/WHEEL
infinity_institute-0.1.0.dist-info/top_level.txt
infinity_institute-0.1.0.dist-info/RECORD
