Metadata-Version: 2.4
Name: infinity-institute
Version: 0.1.0
Summary: Python client for Infinity Media Server - GPU-accelerated image, video, and audio generation
Author: Infinity AI Institute
License-Expression: MIT
Project-URL: Homepage, https://github.com/Infinity-AI-Institute/video-image-audio-serving
Project-URL: Repository, https://github.com/Infinity-AI-Institute/video-image-audio-serving
Project-URL: Changelog, https://github.com/Infinity-AI-Institute/video-image-audio-serving/blob/main/src/infinity_institute/CHANGELOG.md
Keywords: ai,gpu,image-generation,video-generation,text-to-speech,flux,diffusion,infinity-institute
Classifier: Development Status :: 3 - Alpha
Classifier: Intended Audience :: Developers
Classifier: Programming Language :: Python :: 3
Classifier: Programming Language :: Python :: 3.10
Classifier: Programming Language :: Python :: 3.11
Classifier: Programming Language :: Python :: 3.12
Classifier: Topic :: Scientific/Engineering :: Artificial Intelligence
Requires-Python: >=3.10
License-File: LICENSE
Requires-Dist: httpx>=0.25.0
Provides-Extra: dev
Requires-Dist: pytest>=7.0.0; extra == "dev"
Requires-Dist: pytest-asyncio>=0.21.0; extra == "dev"
Requires-Dist: ruff>=0.1.0; extra == "dev"
Requires-Dist: pyright>=1.1.0; extra == "dev"
Dynamic: license-file
